{
  "mapImage": "https://upload.wikimedia.org/wikipedia/commons/6/61/Bahrain_International_Circuit--Outer_Circuit.svg",
  "pins": [
    {
      "id": "1769173116891",
      "x": 1.6484788838394073,
      "y": 94.33422827044863,
      "gear": "1",
      "minSpd": "55",
      "exitSpd": "130",
      "note": "看到路肩直接重刹，吃满两侧路肩，过最后一条线半个车身再开始打方向.\n到 T2 时至少要 130"
    },
    {
      "id": "1769173223331",
      "x": 10.17020291197499,
      "y": 7.370934355337856,
      "gear": "1",
      "minSpd": "95",
      "exitSpd": "105",
      "note": "100 米牌刹车，吃满路肩，50 米牌开始打方向，循迹。\n出路肩后至少要 105"
    },
    {
      "id": "1769173344076",
      "x": 44.16447158942889,
      "y": 4.616440882913532,
      "gear": "2",
      "minSpd": "97",
      "exitSpd": "150",
      "note": "车头即将指向 T7 的时候就可以开始刹了\n重刹快送 30% 左右开始循迹"
    },
    {
      "id": "1769173428138",
      "x": 96.86948215474571,
      "y": 84.10325251572972,
      "gear": "2",
      "minSpd": "105",
      "exitSpd": "180",
      "note": "100 米重刹，过 50 米牌半个车身开始打方向循迹，"
    }
  ]
}
